hmirls/__init__.py
hmirls/operators.py
hmirls/problem.py
hmirls/regularization.py
hmirls/svd.py
hmirls/util.py
hmirls/weighted_least_squares.py
hmirls-0.1.0.dist-info/METADATA
hmirls-0.1.0.dist-info/WHEEL
hmirls-0.1.0.dist-info/LICENSE
hmirls-0.1.0.dist-info/RECORD
