Metadata-Version: 2.1
Name: hmirls
Version: 0.1.0
Summary: Library for Schatten-p norm minimization via iteratively reweighted least squares
License: MIT
Author: Kristof Schroeder
Author-email: kristof_schroeder@web.de
Requires-Python: >=3.8,<3.12
Classifier: License :: OSI Approved :: MIT License
Classifier: Programming Language :: Python :: 3
Classifier: Programming Language :: Python :: 3.8
Classifier: Programming Language :: Python :: 3.9
Classifier: Programming Language :: Python :: 3.10
Classifier: Programming Language :: Python :: 3.11
Requires-Dist: numpy (>=1.24.1,<2.0.0)
Requires-Dist: scipy (>=1.10.0,<2.0.0)
